SimpleDocumentStore/AWSS3.py
SimpleDocumentStore/File.py
SimpleDocumentStore/FileStorageMode.py
SimpleDocumentStore/FileSystem.py
SimpleDocumentStore/IFileStorageMode.py
SimpleDocumentStore/PreValidations.py
SimpleDocumentStore/__init__.py
SimpleDocumentStore-0.1.dist-info/LICENSE.txt
SimpleDocumentStore-0.1.dist-info/METADATA
SimpleDocumentStore-0.1.dist-info/RECORD
SimpleDocumentStore-0.1.dist-info/WHEEL
SimpleDocumentStore-0.1.dist-info/top_level.txt
