Metadata-Version: 2.1
Name: SimpleDocumentStore
Version: 0.1
Summary: A library to store the documents to the local file system and AWS S3
Home-page: https://github.com/reetikaSR/SimpleDocumentStore
Author: reetikaS
License: UNKNOWN
Platform: UNKNOWN
Classifier: Programming Language :: Python :: 3.6
Classifier: License :: OSI Approved :: MIT License
Requires-Dist: boto3
Requires-Dist: botocore
